monz/__init__.py
monz/__main__.py
monz/command_line.py
monz/utils.py
monz-1.1.1.dist-info/entry_points.txt
monz-1.1.1.dist-info/LICENSE
monz-1.1.1.dist-info/WHEEL
monz-1.1.1.dist-info/METADATA
monz-1.1.1.dist-info/RECORD
