Metadata-Version: 2.1
Name: monz
Version: 1.1.1
Summary: Simple CLI for your Monzo account.
Keywords: monzo,cli
Author-email: Paweł Adamczak <pawel.ad@gmail.com>
Requires-Python: >=3.8
Classifier: Development Status :: 5 - Production/Stable
Classifier: Environment :: Console
Classifier: Intended Audience :: End Users/Desktop
Classifier: License :: OSI Approved :: Mozilla Public License 2.0 (MPL 2.0)
Classifier: Operating System :: OS Independent
Classifier: Programming Language :: Python
Classifier: Programming Language :: Python :: 3
Classifier: Programming Language :: Python :: 3.8
Classifier: Programming Language :: Python :: 3.9
Classifier: Programming Language :: Python :: 3.10
Classifier: Programming Language :: Python :: 3.11
Classifier: Programming Language :: Python :: 3.12
Classifier: Topic :: Utilities
Requires-Dist: Babel
Requires-Dist: click
Requires-Dist: click-default-group
Requires-Dist: pymonzo>=2.2.1
Requires-Dist: rich
Requires-Dist: rich-click
Requires-Dist: monz[tests,docs] ; extra == "dev"
Requires-Dist: black ; extra == "dev"
Requires-Dist: interrogate ; extra == "dev"
Requires-Dist: isort ; extra == "dev"
Requires-Dist: ruff ; extra == "dev"
Requires-Dist: mypy ; extra == "dev"
Requires-Dist: flit ; extra == "dev"
Requires-Dist: nox ; extra == "dev"
Requires-Dist: mkdocs ; extra == "docs"
Requires-Dist: mkdocs-gen-files ; extra == "docs"
Requires-Dist: mkdocs-include-markdown-plugin ; extra == "docs"
Requires-Dist: mkdocs-literate-nav ; extra == "docs"
Requires-Dist: mkdocs-material ; extra == "docs"
Requires-Dist: mkdocs-section-index ; extra == "docs"
Requires-Dist: mkdocstrings[python] ; extra == "docs"
Requires-Dist: coverage[toml] ; extra == "tests"
Requires-Dist: polyfactory ; extra == "tests"
Requires-Dist: pytest ; extra == "tests"
Requires-Dist: pytest-mock ; extra == "tests"
Requires-Dist: time-machine ; extra == "tests"
Project-URL: Documentation, https://monz.readthedocs.io/
Project-URL: GitHub, https://github.com/pawelad/monz
Project-URL: Homepage, https://monz.pawelad.dev/
Project-URL: Issues, https://github.com/pawelad/monz/issues
Provides-Extra: dev
Provides-Extra: docs
Provides-Extra: tests
